CAPTCHASOLVERTIKTOKT/__init__.py
CAPTCHASOLVERTIKTOKT/solver.py
captchasolvertiktokt-0.1.0.dist-info/licenses/LICENSE.yaml
captchasolvertiktokt-0.1.0.dist-info/METADATA
captchasolvertiktokt-0.1.0.dist-info/WHEEL
captchasolvertiktokt-0.1.0.dist-info/top_level.txt
captchasolvertiktokt-0.1.0.dist-info/RECORD
